autosarimax/__init__.py
autosarimax/model.py
autosarimax-0.1.1.dist-info/METADATA
autosarimax-0.1.1.dist-info/WHEEL
autosarimax-0.1.1.dist-info/licenses/LICENSE
autosarimax-0.1.1.dist-info/RECORD
