Metadata-Version: 2.4
Name: autosarimax
Version: 0.1.1
Summary: Using the River and Optuna packages to provide an automatically optimized ARIMA-derived model with the possibility of online updates.
License-File: LICENSE
Author: danttis
Author-email: juniordante01@gmail.com
Requires-Python: >=3.9
Classifier: Programming Language :: Python :: 3
Classifier: Programming Language :: Python :: 3.9
Classifier: Programming Language :: Python :: 3.10
Classifier: Programming Language :: Python :: 3.11
Classifier: Programming Language :: Python :: 3.12
Classifier: Programming Language :: Python :: 3.13
Classifier: Programming Language :: Python :: 3.14
Requires-Dist: holidays
Requires-Dist: numpy
Requires-Dist: optuna
Requires-Dist: pandas
Requires-Dist: river
